 [
    {
      "name": "columns",
      "preview": true,
      "docTable": true,
      "reference": "https://www.hlx.live/developer/block-collection/columns",
      "icon": "columns"
    },
    {
      "name": "embed",
      "preview": true,
      "docTable": true,
      "reference": "https://www.hlx.live/developer/block-collection/columns",
      "icon": "anchor"
       
    },
    {
      "name": "form",
      "preview": true,
      "docTable": true,
      "reference": "https://img.icons8.com/ios/512/test.png",
      "icon": "rectangle-list"
      
    },
    {
      "name": "metadata",
      "preview": true,
      "docTable": true,
      "reference": "https://www.hlx.live/developer/block-collection/columns",
      "icon": "file-invoice"
      
    },
    {
      "name": "poll",
      "preview": true,
      "docTable": true,
      "reference": "https://www.hlx.live/developer/block-collection/columns",
      "icon": "survey-poll-horizontal"
    },
    {
      "name": "section-background",
      "preview": true,
      "docTable": true,
      "reference": "https://www.hlx.live/developer/block-collection/columns",
      "icon": "puzzle-piece"
    },
    {
      "name": "winners-carousel",
      "preview": true,
      "docTable": true,
      "reference": "https://www.hlx.live/developer/block-collection/columns",
      "icon": "slideshare"
    },
    {
      "name": "section-bar",
      "preview": true,
      "docTable": true,
      "reference": "https://www.hlx.live/developer/block-collection/columns",
      "icon": "bars"
    }
]
